barka/__init__.py
barka/barka.py
barka-0.0.11.dist-info/LICENSE
barka-0.0.11.dist-info/METADATA
barka-0.0.11.dist-info/WHEEL
barka-0.0.11.dist-info/top_level.txt
barka-0.0.11.dist-info/RECORD
