Metadata-Version: 2.1
Name: barka
Version: 0.0.11
Summary: Barka
Home-page: 
Download-URL: 
Author: Maria
Author-email: stoklosama@gmail.com
Keywords: barka
Classifier: Programming Language :: Python :: 3
Classifier: License :: OSI Approved :: MIT License
Classifier: Operating System :: OS Independent
License-File: LICENSE
Requires-Dist: requests
